Cryptizia/CaeserCipher.py
Cryptizia/CaeserCipherExample.py
Cryptizia/PlayfairCipherExample.py
Cryptizia/__init__.py
Cryptizia-0.3.0.dist-info/METADATA
Cryptizia-0.3.0.dist-info/WHEEL
Cryptizia-0.3.0.dist-info/top_level.txt
Cryptizia-0.3.0.dist-info/RECORD
