Metadata-Version: 2.1
Name: Cryptizia
Version: 0.3.0
Summary: A Python library for various cipher techniques including the Caesar cipher and Playfair cipher examples.
Author: Zia Ur Rehman
Author-email: engrziaurrehman.kicsit@gmail.com
Classifier: Programming Language :: Python :: 3
Classifier: License :: OSI Approved :: MIT License
Classifier: Operating System :: OS Independent
Requires-Python: >=3.6
Requires-Dist: termcolor
